[
  {
    "type": "custom",
    "value": [
      {
        "type": "verbal",
        "value": "In this lesson, we're going to learn one new letter and one new sound."
      },
      {
        "type": "verbal",
        "value": "But like usual, let's review some of the letters, sounds, and words we learned in the previous lessons."
      }
    ]
  },
  {
    "type": "find-grapheme",
    "grapheme": "E",
    "graphemes": ["D", "H"],
    "total": 3,
    "unique": 3,
    "correct": 1
  },
  {
    "type": "find-grapheme",
    "grapheme": "C",
    "graphemes": ["G", "M"],
    "total": 3,
    "unique": 3,
    "correct": 1
  },
  { "type": "sound-to-grapheme", "phoneme": "/t/", "grapheme": "T" },
  { "type": "sound-to-grapheme", "grapheme": "C", "phoneme": "/c/" },
  {
    "type": "sound-to-grapheme",
    "phoneme": "/m/",
    "grapheme": "M",
    "graphemes": ["P", "N"]
  },
  {
    "type": "sound-to-grapheme",
    "phoneme": "/s/",
    "grapheme": "S",
    "graphemes": ["B", "E"]
  },
  {
    "type": "custom",
    "value": [
      {
        "type": "verbal",
        "value": "Let’s practice some words that make a funny S sound. Read the words on the cards one at a time."
      },
      { "type": "card-stack", "values": ["as", "has", "his", "is"] }
    ]
  },
  {
    "type": "custom",
    "value": [
      {
        "type": "verbal",
        "value": "Let’s practice the three heart words we learned. Read the words on the cards one at a time."
      },
      { "type": "card-stack", "values": ["I", "a", "the"] }
    ]
  },
  {
    "type": "grapheme-trace-air",
    "grapheme": "U",
    "pre": {
      "prepend": ["Now it's time to learn a new letter. This is the letter U."]
    }
  },
  { "type": "grapheme-trace-palm", "grapheme": "U" },
  {
    "type": "find-grapheme",
    "grapheme": "U",
    "graphemes": ["C", "E"],
    "total": 3,
    "unique": 3,
    "correct": 1
  },
  { "type": "introduce-sound", "grapheme": "U", "phoneme": "/u/" },
  {
    "type": "sound-in-word",
    "grapheme": "U",
    "phoneme": "/u/",
    "words": [
      { "text": "upper", "correct": true },
      { "text": "cub", "correct": true },
      { "text": "butter", "correct": true },
      { "text": "baby", "correct": false }
    ]
  },
  {
    "type": "custom",
    "value": [
      { "type": "verbal", "value": "Amazing! You know 16 letters now!" },
      {
        "type": "verbal",
        "value": "Alright, now it's time for some Tap-Tap-Slide! As a reminder, in this game, we tap our arm as we make the sound of each letter in order, and then slide them altogether. I'll go first, and then you."
      }
    ]
  },
  {
    "type": "touch-slide",
    "word": "LUG",
    "phonemes": ["/l/", "/u/", "/g/"],
    "post": {
      "append": [
        {
          "type": "verbal",
          "value": "What does it mean to lug something? To lug something means to carry something big or heavy, and it takes a LOT of effort."
        }
      ]
    }
  },
  {
    "type": "touch-slide",
    "word": "DUST",
    "phonemes": ["/d/", "/u/", "/s/", "/t/"]
  },
  {
    "type": "touch-slide",
    "word": "CUSP",
    "phonemes": ["/c/", "/u/", "/s/", "/p/"],
    "post": {
      "append": [
        {
          "type": "verbal",
          "value": "Have you ever heard this word before. It might sound a little silly, but it can mean two different things. One is for example, if you’re “on the cusp of a new school year”, it means the school year is about to start, or if you are “at the cusp of the mountain”, it means you’re almost at the top or point."
        }
      ]
    }
  },
  {
    "type": "touch-slide",
    "word": "MUST",
    "phonemes": ["/m/", "/u/", "/s/", "/t/"]
  },
  { "type": "picture-to-word", "word": "sun", "words": ["sun", "cap", "bus"] },
  {
    "type": "find-picture",
    "words": [
      { "word": "bus", "correct": true },
      { "word": "airplane", "correct": false },
      { "word": "car", "correct": false }
    ]
  },
  {
    "type": "find-picture",
    "words": [
      { "word": "step", "correct": true },
      { "word": "slide", "correct": false },
      { "word": "swing", "correct": false }
    ]
  },
  {
    "type": "custom",
    "value": [
      { "type": "verbal", "value": "You're doing amazing!" },
      {
        "type": "verbal",
        "value": "Let's read another story together. It's my job to read the blue words, and it's your job to read the black words."
      },
      {
        "type": "verbal",
        "value": "We're not going to touch the screen, but I'm going to point to where we're reading with my finger for now, to help you keep track of where we are."
      },
      { "type": "verbal", "value": "Now, let's read a book!" }
    ]
  },
  { "type": "books", "books": [52233] }
]
