[
  {
    "type": "custom",
    "value": [
      {
        "type": "verbal",
        "value": "In this lesson, we're going to learn one new letter and one new sound."
      },
      {
        "type": "verbal",
        "value": "But first, let's review some of the letters and sounds we learned in previous lessons."
      }
    ]
  },
  {
    "type": "find-grapheme",
    "grapheme": "O",
    "graphemes": ["D", "G"],
    "total": 3,
    "unique": 3,
    "correct": 1
  },
  {
    "type": "find-grapheme",
    "grapheme": "P",
    "graphemes": ["R", "S"],
    "total": 3,
    "unique": 3,
    "correct": 1
  },
  {
    "type": "sound-to-grapheme",
    "phoneme": "/i/",
    "grapheme": "I"
  },
  {
    "type": "sound-to-grapheme",
    "grapheme": "A",
    "phoneme": "/a/"
  },
  {
    "type": "sound-to-grapheme",
    "phoneme": "/o/",
    "grapheme": "O",
    "graphemes": ["M", "T"]
  },
  {
    "type": "sound-to-grapheme",
    "phoneme": "/b/",
    "grapheme": "B",
    "graphemes": ["R", "S"]
  },
  {
    "type": "sound-to-grapheme",
    "phoneme": "/g/",
    "grapheme": "G",
    "graphemes": ["C", "Q"]
  },
  {
    "type": "grapheme-trace-air",
    "grapheme": "S",
    "pre": {
      "value": [
        "In the previous lesson, we learned that the letter S can make two different sounds when it is at the end of a word. What are those two sounds?"
      ]
    },
    "post": {
      "value": [
        {
          "type": "verbal",
          "value": [
            "That's right! The letter S when it's at the end of a word can make the ",
            {
              "type": "sound",
              "phoneme": "/s/"
            },
            " sound or the ",
            {
              "type": "sound",
              "phoneme": "/z/"
            },
            " sound."
          ]
        }
      ]
    }
  },
  {
    "type": "card-stack",
    "values": ["is", "mats", "digs"],
    "pre": {
      "value": [
        "Let’s practice some words that end in the letter S. Read the words one at a time."
      ]
    }
  },
  {
    "type": "grapheme-trace-air",
    "grapheme": "E",
    "pre": {
      "prepend": ["Now it's time to learn a new letter."]
    }
  },
  {
    "type": "grapheme-trace-palm",
    "grapheme": "E"
  },
  {
    "type": "find-grapheme",
    "grapheme": "E",
    "graphemes": ["B", "A"],
    "total": 3,
    "unique": 3,
    "correct": 1
  },
  {
    "type": "introduce-sound",
    "grapheme": "E",
    "phoneme": "/e/",
    "post": {
      "insert_after": [
        {
          "index": 0,
          "value": {
            "type": "instruction",
            "value": [
              "The ",
              {
                "type": "sound",
                "phoneme": "/e/"
              },
              " sound can often be a difficult sound for new readers, so spend time to make sure {name} is saying it correctly."
            ]
          }
        }
      ]
    }
  },
  {
    "type": "phoneme-blending",
    "phoneme": "/e/",
    "words": ["bed", "egg", "set"]
  },
  {
    "confetti": true,
    "type": "custom",
    "value": [
      "Amazing, you've learned 12 letters and 13 sounds!",
      {
        "type": "gif-video",
        "src": "/l2r/vods/letter-words-3-letters.mov",
        "width": 200,
        "height": 200
      },
      {
        "type": "verbal",
        "value": [
          "Now it’s time to practice ",
          {
            "type": "text",
            "value": "Finger Words",
            "css": {
              "fontWeight": "bold"
            }
          },
          " again!"
        ]
      }
    ]
  },
  {
    "type": "finger-word",
    "word": "PET",
    "phonemes": ["/p/", "/e/", "/t/"]
  },
  {
    "type": "finger-word",
    "word": "BEST",
    "phonemes": ["/b/", "/e/", "/s/", "/t/"]
  },

  {
    "type": "finger-word",
    "word": "TENT",
    "phonemes": ["/t/", "/e/", "/n/", "/t/"],
    "pre": {
      "replace": [
        {
          "index": 1,
          "value": "We're going to practice Imaginary Finger Words again.  As a reminder, instead of using your fingers and hands physically, you'll perform all the movements entirely in your imagination."
        },
        {
          "index": 2,
          "value": "In your mind, assign each letter to an imaginary finger."
        },
        {
          "index": 3,
          "value": "Say the sound each letter makes."
        }
      ]
    },
    "post": {
      "value": [
        "Are there any sticky sounds?",
        {
          "type": "verbal",
          "value": [
            "Yes, the ",
            {
              "type": "sound",
              "phoneme": "/t/",
              "showQuotes": false
            },
            " sound is a sticky sound."
          ]
        },
        {
          "type": "verbal",
          "value": [
            "Does the ",
            {
              "type": "sound",
              "phoneme": "/t/",
              "showQuotes": false
            },
            " sound have a sound after it to stick to?"
          ]
        },
        {
          "type": "verbal",
          "value": [
            "Yes, the ",
            {
              "type": "sound",
              "phoneme": "/e/",
              "showQuotes": false
            },
            " sound is after the first ",
            {
              "type": "sound",
              "phoneme": "/t/",
              "showQuotes": false
            },
            " sound which means that the first ",
            {
              "type": "sound",
              "phoneme": "/t/",
              "showQuotes": false
            },
            " sound can stick to the ",
            {
              "type": "sound",
              "phoneme": "/e/",
              "showQuotes": false
            },
            " sound. Move those fingers together."
          ]
        }
      ]
    }
  },
  {
    "type": "finger-word",
    "phonemes": ["/t/", "/e/", "/n/", "/t/"],
    "word": "TENT",
    "pre": {
      "value": [
        {
          "type": "verbal",
          "value": [
            "There isn't a sound after the second  ",
            {
              "type": "sound",
              "phoneme": "/t/",
              "showQuotes": false
            },
            " sound, however, so we don't need to do anything special with the second ",
            {
              "type": "sound",
              "phoneme": "/t/",
              "showQuotes": false
            },
            " sound."
          ]
        },
        {
          "type": "verbal",
          "value": [
            {
              "type": "sound",
              "phoneme": "/t/",
              "showQuotes": false,
              "showRightSoundIndicator": false
            },
            {
              "type": "sound",
              "phoneme": "/e/",
              "showQuotes": false,
              "showLeftSoundIndicator": false
            },
            " - ",
            {
              "type": "sound",
              "phoneme": "/n/",
              "showQuotes": false
            },
            " - ",
            {
              "type": "sound",
              "phoneme": "/t/",
              "showQuotes": false
            }
          ]
        },

        "We have a gap between the sounds currently, just like there is a gap between our imaginary fingers (and finger pairs).",
        "We want to blend the sounds together, so there's no gap between the sounds, just like we do on our knuckles in Finger Words."
      ]
    },
    "post": {
      "value": [
        "Say the sound that each finger or finger pair makes slowly and continuously, blending the sounds together without any gaps.",
        {
          "type": "verbal",
          "value": [
            {
              "type": "sound",
              "phoneme": "/t/",
              "showQuotes": false,
              "showRightSoundIndicator": false
            },
            {
              "type": "sound",
              "phoneme": "/e/",
              "showQuotes": false,
              "showLeftSoundIndicator": false
            },
            " ",
            {
              "type": "sound",
              "phoneme": "/n/",
              "showQuotes": false
            },
            " ",
            {
              "type": "sound",
              "phoneme": "/t/",
              "showQuotes": false
            }
          ]
        },
        "Do it again and again, slightly faster each time, until you hear the word.",
        {
          "type": "verbal",
          "value": [
            {
              "type": "sound",
              "phoneme": "/t/",
              "showQuotes": false,
              "showRightSoundIndicator": false
            },
            {
              "type": "sound",
              "phoneme": "/e/",
              "showQuotes": false,
              "showLeftSoundIndicator": false
            },
            " ",
            {
              "type": "sound",
              "phoneme": "/n/",
              "showQuotes": false
            },
            " ",
            {
              "type": "sound",
              "phoneme": "/t/",
              "showQuotes": false
            },
            " . . . ",
            {
              "type": "sound",
              "phoneme": "/t/",
              "showQuotes": false,
              "showRightSoundIndicator": false
            },
            {
              "type": "sound",
              "phoneme": "/e/",
              "showQuotes": false,
              "showLeftSoundIndicator": false
            },
            " ",
            {
              "type": "sound",
              "phoneme": "/n/",
              "showQuotes": false
            },
            " ",
            {
              "type": "sound",
              "phoneme": "/t/",
              "showQuotes": false
            },
            " . . . ",
            {
              "type": "text",
              "value": "TENT",
              "css": {
                "fontWeight": "bold"
              }
            }
          ]
        },
        "Did you hear the word? That's right, the word is ‘tent’."
      ]
    }
  },
  {
    "type": "word-to-picture",
    "word": "BED",
    "words": ["hat", "car"]
  },
  {
    "type": "word-to-picture",
    "word": "NEST",
    "words": ["barn", "bed"]
  },
  {
    "type": "books",
    "books": [52226],
    "pre": {
      "value": [
        "Great work! Now, let's read a book together. I will read the blue words and you will read the black words.",
        "Remember, when it's your turn to read, look at the word and say the sound each part makes. Then put the sounds together to make the word. You can use Finger Words to help you.",
        {
          "type": "instruction",
          "value": "Help {name} read each word using Finger Words. This is not a quiz, so guide them when they get stuck. This is just practice and should be fun."
        }
      ]
    }
  },
  {
    "type": "conclusion",
    "confetti": true
  }
]
